logflow/__init__.py
logflow/logger.py
logflow/config/__init__.py
logflow/config/log_config.py
logflow/formatters/__init__.py
logflow/formatters/formatter.py
logflow/formatters/enums/__init__.py
logflow/formatters/enums/date_time_formats.py
logflow/formatters/impl/__init__.py
logflow/formatters/impl/console_formatter.py
logflow/formatters/impl/dict_formatter.py
logflow/formatters/impl/file_formatter.py
logflow/formatters/impl/json_formatter.py
logflow/formatters/impl/plain_formatter.py
logflow/handlers/__init__.py
logflow/handlers/handler.py
logflow/handlers/impl/__init__.py
logflow/handlers/impl/console.py
logflow/handlers/impl/custom.py
logflow/handlers/impl/file.py
logflow/models/__init__.py
logflow/models/log.py
logflow/models/enums/__init__.py
logflow/models/enums/log_colors.py
logflow/models/enums/log_level.py
logflow/models/enums/log_type.py
tests/__init__.py
logflow_python-1.0.2.dist-info/METADATA
logflow_python-1.0.2.dist-info/WHEEL
logflow_python-1.0.2.dist-info/top_level.txt
logflow_python-1.0.2.dist-info/RECORD
