Metadata-Version: 2.1
Name: logflow-python
Version: 1.0.2
Summary: A simple but modular logging library for Python applications.
Home-page: https://github.com/aleko-khomasuridze/LogFlow
Author: Aleko Khomasuridze
Author-email: aleko.khomasurize@gmail.com
License: UNKNOWN
Platform: UNKNOWN
Classifier: Programming Language :: Python :: 3
Classifier: License :: OSI Approved :: MIT License
Classifier: Operating System :: OS Independent
Requires-Python: >=3.8
Requires-Dist: colorama
